README.md
setup.py
telero/__init__.py
telero/client.py
telero/filters.py
telero/namedtuple.py
telero/objects.py
telero.egg-info/PKG-INFO
telero.egg-info/SOURCES.txt
telero.egg-info/dependency_links.txt
telero.egg-info/requires.txt
telero.egg-info/top_level.txt
telero/telepot/__init__.py
telero/telepot/api.py
telero/telepot/delegate.py
telero/telepot/exception.py
telero/telepot/filtering.py
telero/telepot/hack.py
telero/telepot/helper.py
telero/telepot/loop.py
telero/telepot/namedtuple.py
telero/telepot/routing.py
telero/telepot/text.py